Metadata-Version: 1.1
Name: pyembedded
Version: 1.11
Summary: Python library to interface basic embedded modules like RFID, GPS, GSM, LCD (16x2), DC Motor
Home-page: UNKNOWN
Author: Abhinav Rawat
Author-email: abhinavrawat92@gmail.com
License: MIT
Keywords: embedded,rfid,gsm,gps,lcd,motor,raspberry pi
Platform: UNKNOWN
Classifier: Development Status :: 5 - Production/Stable
Classifier: Intended Audience :: Education
Classifier: Operating System :: Microsoft :: Windows :: Windows 10
Classifier: License :: OSI Approved :: MIT License
Classifier: Programming Language :: Python :: 3
